{
  "terraform_type": "aws_transfer_agreement",
  "struct_type": "",
  "namespace": "github.com/hashicorp/terraform-provider-aws/internal/service/transfer",
  "registration_method": "SDKResources",
  "sdk_type": "aws_sdk",
  "schema_index": "func.resourceTransferAgreement.goindex",
  "create_index": "func.resourceAgreementCreate.goindex",
  "read_index": "func.resourceAgreementRead.goindex",
  "update_index": "func.resourceAgreementUpdate.goindex",
  "delete_index": "func.resourceAgreementDelete.goindex",
  "attribute_index": "func.resourceTransferAgreement.goindex"
}