{
  "terraform_type": "aws_transfer_connector",
  "struct_type": "",
  "namespace": "github.com/hashicorp/terraform-provider-aws/internal/service/transfer",
  "registration_method": "SDKResources",
  "sdk_type": "aws_sdk",
  "schema_index": "func.resourceTransferConnector.goindex",
  "create_index": "func.resourceConnectorCreate.goindex",
  "read_index": "func.resourceConnectorRead.goindex",
  "update_index": "func.resourceConnectorUpdate.goindex",
  "delete_index": "func.resourceConnectorDelete.goindex",
  "attribute_index": "func.resourceTransferConnector.goindex"
}