{
  "terraform_type": "aws_s3control_access_point_policy",
  "struct_type": "",
  "namespace": "github.com/hashicorp/terraform-provider-aws/internal/service/s3control",
  "registration_method": "SDKResources",
  "sdk_type": "aws_sdk",
  "schema_index": "func.resourceS3controlAccessPointPolicy.goindex",
  "create_index": "func.resourceAccessPointPolicyCreate.goindex",
  "read_index": "func.resourceAccessPointPolicyRead.goindex",
  "update_index": "func.resourceAccessPointPolicyUpdate.goindex",
  "delete_index": "func.resourceAccessPointPolicyDelete.goindex",
  "attribute_index": "func.resourceS3controlAccessPointPolicy.goindex"
}