{
  "terraform_type": "aws_cloudformation_stack",
  "struct_type": "",
  "namespace": "github.com/hashicorp/terraform-provider-aws/internal/service/cloudformation",
  "registration_method": "SDKResources",
  "sdk_type": "aws_sdk",
  "schema_index": "func.resourceCloudformationStack.goindex",
  "create_index": "func.resourceStackCreate.goindex",
  "read_index": "func.resourceStackRead.goindex",
  "update_index": "func.resourceStackUpdate.goindex",
  "delete_index": "func.resourceStackDelete.goindex",
  "attribute_index": "func.resourceCloudformationStack.goindex"
}