{
  "terraform_type": "aws_datasync_location_efs",
  "struct_type": "",
  "namespace": "github.com/hashicorp/terraform-provider-aws/internal/service/datasync",
  "registration_method": "SDKResources",
  "sdk_type": "aws_sdk",
  "schema_index": "func.resourceDatasyncLocationEfs.goindex",
  "create_index": "func.resourceLocationEFSCreate.goindex",
  "read_index": "func.resourceLocationEFSRead.goindex",
  "update_index": "func.resourceLocationEFSUpdate.goindex",
  "delete_index": "func.resourceLocationEFSDelete.goindex",
  "attribute_index": "func.resourceDatasyncLocationEfs.goindex"
}