{
  "terraform_type": "aws_ram_resource_share",
  "struct_type": "",
  "namespace": "github.com/hashicorp/terraform-provider-aws/internal/service/ram",
  "registration_method": "SDKResources",
  "sdk_type": "aws_sdk",
  "schema_index": "func.resourceRamResourceShare.goindex",
  "create_index": "func.resourceResourceShareCreate.goindex",
  "read_index": "func.resourceResourceShareRead.goindex",
  "update_index": "func.resourceResourceShareUpdate.goindex",
  "delete_index": "func.resourceResourceShareDelete.goindex",
  "attribute_index": "func.resourceRamResourceShare.goindex"
}