{
  "terraform_type": "aws_db_snapshot_copy",
  "struct_type": "",
  "namespace": "github.com/hashicorp/terraform-provider-aws/internal/service/rds",
  "registration_method": "SDKResources",
  "sdk_type": "aws_sdk",
  "schema_index": "func.resourceDbSnapshotCopy.goindex",
  "create_index": "func.resourceSnapshotCopyCreate.goindex",
  "read_index": "func.resourceSnapshotCopyRead.goindex",
  "update_index": "func.resourceSnapshotCopyUpdate.goindex",
  "delete_index": "func.resourceSnapshotCopyDelete.goindex",
  "attribute_index": "func.resourceDbSnapshotCopy.goindex"
}