{
  "terraform_type": "aws_keyspaces_keyspace",
  "struct_type": "",
  "namespace": "github.com/hashicorp/terraform-provider-aws/internal/service/keyspaces",
  "registration_method": "SDKResources",
  "sdk_type": "aws_sdk",
  "schema_index": "func.resourceKeyspacesKeyspace.goindex",
  "create_index": "func.resourceKeyspaceCreate.goindex",
  "read_index": "func.resourceKeyspaceRead.goindex",
  "update_index": "func.resourceKeyspaceUpdate.goindex",
  "delete_index": "func.resourceKeyspaceDelete.goindex",
  "attribute_index": "func.resourceKeyspacesKeyspace.goindex"
}