{
  "terraform_type": "aws_elb",
  "struct_type": "",
  "namespace": "github.com/hashicorp/terraform-provider-aws/internal/service/elb",
  "registration_method": "SDKResources",
  "sdk_type": "aws_sdk",
  "schema_index": "func.resourceElb.goindex",
  "create_index": "func.resourceLoadBalancerCreate.goindex",
  "read_index": "func.resourceLoadBalancerRead.goindex",
  "update_index": "func.resourceLoadBalancerUpdate.goindex",
  "delete_index": "func.resourceLoadBalancerDelete.goindex",
  "attribute_index": "func.resourceElb.goindex"
}