{
  "terraform_type": "aws_organizations_policy",
  "struct_type": "",
  "namespace": "github.com/hashicorp/terraform-provider-aws/internal/service/organizations",
  "registration_method": "SDKResources",
  "sdk_type": "aws_sdk",
  "schema_index": "func.resourceOrganizationsPolicy.goindex",
  "create_index": "func.resourcePolicyCreate.goindex",
  "read_index": "func.resourcePolicyRead.goindex",
  "update_index": "func.resourcePolicyUpdate.goindex",
  "delete_index": "func.resourcePolicyDelete.goindex",
  "attribute_index": "func.resourceOrganizationsPolicy.goindex"
}