{
  "terraform_type": "aws_auditmanager_framework_share",
  "struct_type": "frameworkShareResource",
  "namespace": "github.com/hashicorp/terraform-provider-aws/internal/service/auditmanager",
  "registration_method": "FrameworkResources",
  "sdk_type": "aws_framework",
  "schema_index": "method.frameworkShareResource.Schema.goindex",
  "create_index": "method.frameworkShareResource.Create.goindex",
  "read_index": "method.frameworkShareResource.Read.goindex",
  "update_index": "method.frameworkShareResource.Update.goindex",
  "delete_index": "method.frameworkShareResource.Delete.goindex",
  "attribute_index": "method.frameworkShareResource.Schema.goindex"
}